{
  "parent": "minecraft:recipes/root",
  "rewards": {
    "recipes": [
      "kindredlegacy:firaga_essence"
    ]
  },
  "criteria": {
    "has_fire_resistance_powder": {
      "trigger": "minecraft:inventory_changed",
      "conditions": {
        "items": [
          {
            "item": "kindredlegacy:fire_resistance_powder"
          }
        ]
      }
    },
    "has_life_boost": {
      "trigger": "minecraft:inventory_changed",
      "conditions": {
        "items": [
          {
            "item": "kindredlegacy:life_boost"
          }
        ]
      }
    },
    "has_chargestone": {
      "trigger": "minecraft:inventory_changed",
      "conditions": {
        "items": [
          {
            "item": "kindredlegacy:chargestone"
          }
        ]
      }
    },
    "has_the_recipe": {
      "trigger": "minecraft:recipe_unlocked",
      "conditions": {
        "recipe": "kindredlegacy:firaga_essence"
      }
    }
  },
  "requirements": [
    [
      "has_fire_resistance_powder",
      "has_life_boost",
      "has_chargestone",
      "has_the_recipe"
    ]
  ]
}