{
  "parent": "minecraft:recipes/root",
  "rewards": {
    "recipes": [
      "kindredlegacy:invisibility_powder"
    ]
  },
  "criteria": {
    "has_verdantizer": {
      "trigger": "minecraft:inventory_changed",
      "conditions": {
        "items": [
          {
            "item": "kindredlegacy:verdantizer"
          }
        ]
      }
    },
    "has_blaze_powder": {
      "trigger": "minecraft:inventory_changed",
      "conditions": {
        "items": [
          {
            "item": "minecraft:blaze_powder"
          }
        ]
      }
    },
    "has_nether_wart": {
      "trigger": "minecraft:inventory_changed",
      "conditions": {
        "items": [
          {
            "item": "minecraft:nether_wart"
          }
        ]
      }
    },
    "has_golden_carrot": {
      "trigger": "minecraft:inventory_changed",
      "conditions": {
        "items": [
          {
            "item": "minecraft:golden_carrot"
          }
        ]
      }
    },
    "has_the_recipe": {
      "trigger": "minecraft:recipe_unlocked",
      "conditions": {
        "recipe": "kindredlegacy:invisibility_powder"
      }
    }
  },
  "requirements": [
    [
      "has_verdantizer",
      "has_blaze_powder",
      "has_nether_wart",
      "has_golden_carrot",
      "has_the_recipe"
    ]
  ]
}